pyconfiglite/__init__.py
pyconfiglite/config_loader.py
pyconfiglite/exceptions.py
pyconfiglite-0.1.3.dist-info/METADATA
pyconfiglite-0.1.3.dist-info/WHEEL
pyconfiglite-0.1.3.dist-info/licenses/LICENSE
pyconfiglite-0.1.3.dist-info/RECORD
